plone/versioncheck/__init__.py
plone/versioncheck/analyser.py
plone/versioncheck/formatter.py
plone/versioncheck/parser.py
plone/versioncheck/py.typed
plone/versioncheck/pypi.py
plone/versioncheck/script.py
plone/versioncheck/tracking.py
plone/versioncheck/utils.py
plone/versioncheck/tpl/browser.jinja
plone_versioncheck-2.0.1.dist-info/METADATA
plone_versioncheck-2.0.1.dist-info/WHEEL
plone_versioncheck-2.0.1.dist-info/entry_points.txt
plone_versioncheck-2.0.1.dist-info/top_level.txt
plone_versioncheck-2.0.1.dist-info/RECORD
