Metadata-Version: 2.4
Name: plone.versioncheck
Version: 2.0.1
Summary: Checks pinned versions with overrides in a cascaded buildout
Author-email: "Jens W. Klein" <jens@bluedynamics.com>
License: GPL version 2
Project-URL: Source, https://github.com/plone/plone.versioncheck
Project-URL: Issues, https://github.com/plone/plone.versioncheck/issues
Keywords: plone,buildout,version
Classifier: Development Status :: 5 - Production/Stable
Classifier: Framework :: Buildout :: Extension
Classifier: Framework :: Buildout :: Recipe
Classifier: Framework :: Buildout
Classifier: Intended Audience :: Developers
Classifier: License :: OSI Approved :: GNU General Public License v2 (GPLv2)
Classifier: Operating System :: OS Independent
Classifier: Programming Language :: Python :: 3
Classifier: Programming Language :: Python :: 3.10
Classifier: Programming Language :: Python :: 3.11
Classifier: Programming Language :: Python :: 3.12
Classifier: Programming Language :: Python :: 3.13
Classifier: Programming Language :: Python :: 3.14
Classifier: Topic :: Software Development :: Build Tools
Classifier: Topic :: Software Development :: Quality Assurance
Requires-Python: >=3.10
Requires-Dist: colorama
Requires-Dist: httpx<1.0,>=0.27
Requires-Dist: jinja2
Requires-Dist: packaging
Requires-Dist: zc.buildout
Provides-Extra: test
Requires-Dist: pytest; extra == "test"
Requires-Dist: pytest-asyncio; extra == "test"
Requires-Dist: pytest-cov; extra == "test"
Requires-Dist: pytest-mock; extra == "test"
Requires-Dist: pytest-remove-stale-bytecode; extra == "test"
Requires-Dist: pytest-html; extra == "test"
Requires-Dist: respx; extra == "test"
Provides-Extra: typecheck
Requires-Dist: pyright; extra == "typecheck"
Provides-Extra: develop
Requires-Dist: pdbpp; extra == "develop"
Requires-Dist: isort; extra == "develop"
Provides-Extra: docs
Requires-Dist: Sphinx; extra == "docs"
